latin_rectangles/__init__.py
latin_rectangles/__main__.py
latin_rectangles/derangements.py
latin_rectangles/extension_counting.py
latin_rectangles/py.typed
latin_rectangles/rook_polynomials.py
latin_rectangles-0.1.2.dist-info/METADATA
latin_rectangles-0.1.2.dist-info/WHEEL
latin_rectangles-0.1.2.dist-info/entry_points.txt
latin_rectangles-0.1.2.dist-info/licenses/LICENSE
latin_rectangles-0.1.2.dist-info/RECORD
