Metadata-Version: 2.4
Name: latin-rectangles
Version: 0.1.2
Summary: Count the number of one-row extensions of Latin rectangles.
Author-email: Ioannis Michaloliakos <ioannis.michalol@ufl.edu>
License-File: LICENSE
Requires-Python: >=3.12
